[{"folder_name": "cape_town", "name": "Cape Town", "coords": [-33.9221, 18.4231], "country": "south_africa", "country_ISO": "ZA"}, {"folder_name": "hong_kong", "name": "Hong Kong", "coords": [22.279305, 114.161491], "country": "china", "country_ISO": "CN"}, {"folder_name": "uttar_pradesh", "name": "Uttar Pradesh", "coords": [27.1751, 78.0421], "country": "india", "country_ISO": "IN"}, {"folder_name": "jakarta", "name": "Jakarta", "coords": [-6.1377, 106.8172], "country": "indonesia", "country_ISO": "ID"}, {"folder_name": "tokyo", "name": "Tokyo", "coords": [35.6586, 139.7454], "country": "japan", "country_ISO": "JP"}, {"folder_name": "mt_everest", "name": "Mount Everest", "coords": [27.9881, 86.925], "country": "nepal", "country_ISO": "NP"}, {"folder_name": "papua_new_guinea", "name": "Papua New Guinea", "coords": [-4.6797, 143.5427], "country": "papua_new_guinea", "country_ISO": "PG"}, {"folder_name": "seoul", "name": "Seoul", "coords": [37.5519, 126.9918], "country": "korea,_republic_of", "country_ISO": "KR"}, {"folder_name": "moorea", "name": "Mo\u2019orea", "coords": [-17.5388, -149.8295], "country": "france", "country_ISO": "FR"}, {"folder_name": "paris", "name": "Paris", "coords": [48.8575, 2.3514], "country": "france", "country_ISO": "FR"}, {"folder_name": "donegal", "name": "Donegal", "coords": [54.6538, -8.1096], "country": "ireland", "country_ISO": "IE"}, {"folder_name": "dublin", "name": "Dublin", "coords": [53.3498, -6.2603], "country": "united_kingdom", "country_ISO": "GB"}, {"folder_name": "malaga", "name": "M\u00e1laga", "coords": [36.7213, -4.4213], "country": "spain", "country_ISO": "ES"}, {"folder_name": "london", "name": "London", "coords": [51.5072, 0.1276], "country": "united_kingdom", "country_ISO": "GB"}, {"folder_name": "oxford", "name": "Oxford", "coords": [51.752, -1.2577], "country": "united_kingdom", "country_ISO": "GB"}, {"folder_name": "scotland", "name": "Scotland", "coords": [56.4907, -4.2026], "country": "united_kingdom", "country_ISO": "GB"}, {"folder_name": "british_columbia", "name": "British Columbia", "coords": [53.7267, -127.6476], "country": "canada", "country_ISO": "CA"}, {"folder_name": "la_fortuna", "name": "La Fortuna", "coords": [9.7849, -83.7534], "country": "costa_rica", "country_ISO": "CR"}, {"folder_name": "machu_picchu", "name": "Machu Picchu", "coords": [-13.1632, -72.5453], "country": "peru", "country_ISO": "PE"}, {"folder_name": "boston", "name": "Boston", "coords": [42.3601, -71.0589], "country": "united_states", "country_ISO": "US"}, {"folder_name": "grand_canyon", "name": "Grand Canyon", "coords": [36.2679, -112.3535], "country": "united_states", "country_ISO": "US"}, {"folder_name": "sevilla", "name": "Sevilla", "coords": [37.3891, -5.9845], "country": "spain", "country_ISO": "ES"}, {"folder_name": "lund", "name": "Lund", "coords": [55.7047, 13.191], "country": "sweden", "country_ISO": "SE"}, {"folder_name": "shanghai", "name": "Shanghai", "coords": [31.2304, 121.4737], "country": "sweden", "country_ISO": "SE"}, {"folder_name": "british_columbia", "name": "British Columbia", "coords": [53.7267, -127.6476], "country": "canada", "country_ISO": "CA"}, {"folder_name": "phi_phi_island", "name": "Phi Phi Island", "coords": [7.7407, 98.7784], "country": "thailand", "country_ISO": "TH"}, {"folder_name": "maya_bay_island", "name": "Maya Bay Island", "coords": [7.678889, 98.764999], "country": "thailand", "country_ISO": "TH"}, {"folder_name": "koh_samui_island", "name": "Koh Samui Island", "coords": [9.512, 100.0136], "country": "thailand", "country_ISO": "TH"}, {"folder_name": "austin", "name": "Austin", "coords": [30.2672, -97.7431], "country": "united_states", "country_ISO": "US"}, {"folder_name": "duxbury", "name": "Duxbury", "coords": [42.0418, -70.6723], "country": "united_states", "country_ISO": "US"}, {"folder_name": "nice", "name": "Nice", "coords": [43.7102, 7.262], "country": "france", "country_ISO": "FR"}, {"folder_name": "macau", "name": "Macau", "coords": [22.1987, 113.5439], "country": "china", "country_ISO": "CN"}, {"folder_name": "quito", "name": "Quito", "coords": [-0.1807, -78.4678], "country": "ecuador", "country_ISO": "EC"}, {"folder_name": "sydney", "name": "Sydney", "coords": [-33.8688, 151.2093], "country": "australia", "country_ISO": "AU"}, {"folder_name": "maasai_mara", "name": "Maasai Mara", "coords": [-1.4821, 35.13], "country": "kenya", "country_ISO": "KE"}, {"folder_name": "athens", "name": "Athens", "coords": [37.9838, 23.7275], "country": "greece", "country_ISO": "GR"}, {"folder_name": "st_julians", "name": "St. Julian's", "coords": [35.9214, 14.4906], "country": "malta", "country_ISO": "MT"}, {"folder_name": "budapest", "name": "Budapest", "coords": [47.4979, 19.0402], "country": "hungary", "country_ISO": "HU"}, {"folder_name": "friesland", "name": "Friesland", "coords": [53.1642, 5.7818], "country": "netherlands", "country_ISO": "NL"}, {"folder_name": "split", "name": "Split", "coords": [43.5147, 16.4435], "country": "croatia", "country_ISO": "HR"}, {"folder_name": "santa_ana", "name": "Santa Ana", "coords": [33.7455, -117.8677], "country": "el_salvador", "country_ISO": "SV"}, {"folder_name": "cannes", "name": "Cannes", "coords": [43.5539, 7.071], "country": "france", "country_ISO": "FR"}]